flake8_complex_f_strings.py
flake8_complex_f_strings-0.1.0.dist-info/LICENSE
flake8_complex_f_strings-0.1.0.dist-info/METADATA
flake8_complex_f_strings-0.1.0.dist-info/WHEEL
flake8_complex_f_strings-0.1.0.dist-info/entry_points.txt
flake8_complex_f_strings-0.1.0.dist-info/top_level.txt
flake8_complex_f_strings-0.1.0.dist-info/RECORD
